README.md
beancount_ing_diba/__init__.py
beancount_ing_diba/ec.py
beancount_ing_diba-0.5.0.dist-info/LICENSE.txt
beancount_ing_diba-0.5.0.dist-info/WHEEL
beancount_ing_diba-0.5.0.dist-info/METADATA
beancount_ing_diba-0.5.0.dist-info/RECORD
